README.md
setup.py
arzela/__init__.py
arzela/__main__.py
arzela/monitor.py
arzela/proxy.py
arzela.egg-info/PKG-INFO
arzela.egg-info/SOURCES.txt
arzela.egg-info/dependency_links.txt
arzela.egg-info/entry_points.txt
arzela.egg-info/requires.txt
arzela.egg-info/top_level.txt
arzela/worker/__init__.py
arzela/worker/db.py
arzela/worker/example.py
arzela/worker/net_db.py