Metadata-Version: 2.1
Name: arzela
Version: 0.3
Summary: Distributed System Monitor
Home-page: https://github.com/chengscott/arzela
Author: chengscott
Maintainer: chengscott
License: BSD
Platform: UNKNOWN
Classifier: Development Status :: 4 - Beta
Classifier: Environment :: Console
Classifier: Intended Audience :: System Administrators
Classifier: License :: OSI Approved :: BSD License
Classifier: Topic :: System :: Clustering
Classifier: Topic :: System :: Monitoring
